copr_builder/__init__.py
copr_builder/copr_builder.py
copr_builder/copr_project.py
copr_builder/errors.py
copr_builder/git_repo.py
copr_builder/srpm_builder.py
copr_builder/utils.py
copr_builder-1.1.data/scripts/copr-builder
copr_builder-1.1.dist-info/LICENSE
copr_builder-1.1.dist-info/METADATA
copr_builder-1.1.dist-info/WHEEL
copr_builder-1.1.dist-info/top_level.txt
copr_builder-1.1.dist-info/RECORD
