Metadata-Version: 2.1
Name: copr-builder
Version: 1.1
Summary: Python script for building git projects in Copr
Home-page: https://github.com/vojtechtrefny/copr-builder
Author: Vojtech Trefny
Author-email: vtrefny@redhat.com
License: UNKNOWN
Platform: UNKNOWN
License-File: LICENSE
